rainbow/__init__.py
rainbow/datadirectory.py
rainbow/datafile.py
rainbow/agilent/__init__.py
rainbow/agilent/chemstation.py
rainbow/agilent/masshunter.py
rainbow/waters/__init__.py
rainbow/waters/masslynx.py
rainbow_api-1.0.10.dist-info/COPYING
rainbow_api-1.0.10.dist-info/COPYING.LESSER
rainbow_api-1.0.10.dist-info/METADATA
rainbow_api-1.0.10.dist-info/WHEEL
rainbow_api-1.0.10.dist-info/top_level.txt
rainbow_api-1.0.10.dist-info/RECORD
