Metadata-Version: 2.1
Name: rainbow-api
Version: 1.0.10
Summary: Read chromatography and mass spectrometry binary files
Author: Evan Shi and Eugene Kwan
Author-email: evanyshi@cmu.edu
License: COPYING.LESSER
Project-URL: Repository, https://github.com/evanyeyeye/rainbow
Project-URL: Documentation, https://rainbow-api.readthedocs.io
Classifier: License :: OSI Approved :: GNU Lesser General Public License v3 (LGPLv3)
License-File: COPYING
License-File: COPYING.LESSER
Requires-Dist: numpy
Requires-Dist: matplotlib
Requires-Dist: lxml
Requires-Dist: pandas
